{"meta":{"total-pages":191},"links":{"first":"https://machinist-chipmunk-44203.netlify.com/trades?page=0","last":"https://machinist-chipmunk-44203.netlify.com/trades?page=190","next":"https://machinist-chipmunk-44203.netlify.com/trades?page=14","prev":"https://machinist-chipmunk-44203.netlify.com/trades?page=12"},"data":[{"type":"trades","id":"LI5.104","attributes":{"":"","上價":"59.4","下價":"8.6","中價":"30.7","交易日期":"106.06.18","交易量":"3520","作物名稱":"萵苣菜-油麥菜","市場名稱":"台北二","平均價":"32"}},{"type":"trades","id":"LI6.104","attributes":{"":"","上價":"100","下價":"96.2","中價":"100","交易日期":"106.06.18","交易量":"1580","作物名稱":"萵苣菜-蘿美","市場名稱":"台北二","平均價":"99.2"}},{"type":"trades","id":"LI8.104","attributes":{"":"","上價":"87.3","下價":"53.8","中價":"69.7","交易日期":"106.06.18","交易量":"2295","作物名稱":"萵苣菜-水耕","市場名稱":"台北二","平均價":"70.1"}},{"type":"trades","id":"LI9.104","attributes":{"":"","上價":"62.9","下價":"27.9","中價":"52","交易日期":"106.06.18","交易量":"7681","作物名稱":"萵苣菜-進口","市場名稱":"台北二","平均價":"49.4"}},{"type":"trades","id":"LJ4.104","attributes":{"":"","上價":"50","下價":"16.3","中價":"38.3","交易日期":"106.06.18","交易量":"460","作物名稱":"芥菜-小芥菜","市場名稱":"台北二","平均價":"36.3"}},{"type":"trades","id":"LK2.104","attributes":{"":"","上價":"62.6","下價":"15.9","中價":"43.4","交易日期":"106.06.18","交易量":"660","作物名稱":"芥藍菜","市場名稱":"台北二","平均價":"41.7"}},{"type":"trades","id":"LK3.104","attributes":{"":"","上價":"120.5","下價":"100","中價":"100","交易日期":"106.06.18","交易量":"88","作物名稱":"芥藍菜-芥藍芽","市場名稱":"台北二","平均價":"104.1"}},{"type":"trades","id":"LM1.104","attributes":{"":"","上價":"55.7","下價":"36.5","中價":"47.9","交易日期":"106.06.18","交易量":"1265","作物名稱":"莧菜-紅莧菜","市場名稱":"台北二","平均價":"47.1"}},{"type":"trades","id":"LM2.104","attributes":{"":"","上價":"54.7","下價":"38","中價":"48.8","交易日期":"106.06.18","交易量":"1753","作物名稱":"莧菜-白莧菜","市場名稱":"台北二","平均價":"47.8"}},{"type":"trades","id":"LN1.104","attributes":{"":"","上價":"47.4","下價":"15","中價":"35.1","交易日期":"106.06.18","交易量":"2603","作物名稱":"油菜","市場名稱":"台北二","平均價":"33.5"}}]}